httprpc_dengzhenzhen-0.0.3.20210906232540.dist-info/METADATA
httprpc_dengzhenzhen-0.0.3.20210906232540.dist-info/RECORD
httprpc_dengzhenzhen-0.0.3.20210906232540.dist-info/WHEEL
httprpc_dengzhenzhen-0.0.3.20210906232540.dist-info/entry_points.txt
httprpc_dengzhenzhen-0.0.3.20210906232540.dist-info/top_level.txt
setup_demo/FlaskApp.py
setup_demo/Serializer.py
setup_demo/__init__.py
setup_demo/client.py
setup_demo/rpc_client.py
setup_demo/rpc_func.py
setup_demo/rpc_server.py
