Metadata-Version: 2.1
Name: httprpc-dengzhenzhen
Version: 0.0.3.20210906232540
Summary: UNKNOWN
Home-page: UNKNOWN
Author: dengzhenzhen
Author-email: UNKNOWN
License: UNKNOWN
Platform: UNKNOWN
Requires-Dist: Flask
Requires-Dist: requests
